Technology/__init__.py
Technology/math.py
Technology/password.py
Technology_Note_Dev-2023010412.dist-info/LICENSE
Technology_Note_Dev-2023010412.dist-info/METADATA
Technology_Note_Dev-2023010412.dist-info/WHEEL
Technology_Note_Dev-2023010412.dist-info/top_level.txt
Technology_Note_Dev-2023010412.dist-info/RECORD
